odoo/addons/ddmrp_adjustment/README.rst
odoo/addons/ddmrp_adjustment/__init__.py
odoo/addons/ddmrp_adjustment/__manifest__.py
odoo/addons/ddmrp_adjustment/i18n/ddmrp_adjustment.pot
odoo/addons/ddmrp_adjustment/i18n/pt_BR.po
odoo/addons/ddmrp_adjustment/migrations/11.0.1.1.0/post-migration.py
odoo/addons/ddmrp_adjustment/models/__init__.py
odoo/addons/ddmrp_adjustment/models/ddmrp_adjustment.py
odoo/addons/ddmrp_adjustment/models/ddmrp_adjustment_demand.py
odoo/addons/ddmrp_adjustment/models/stock_warehouse_orderpoint.py
odoo/addons/ddmrp_adjustment/readme/CONTRIBUTORS.rst
odoo/addons/ddmrp_adjustment/readme/DESCRIPTION.rst
odoo/addons/ddmrp_adjustment/readme/HISTORY.rst
odoo/addons/ddmrp_adjustment/readme/ROADMAP.rst
odoo/addons/ddmrp_adjustment/readme/USAGE.rst
odoo/addons/ddmrp_adjustment/security/ir.model.access.csv
odoo/addons/ddmrp_adjustment/static/description/icon.png
odoo/addons/ddmrp_adjustment/static/description/index.html
odoo/addons/ddmrp_adjustment/tests/__init__.py
odoo/addons/ddmrp_adjustment/tests/test_adjustment_wizard.py
odoo/addons/ddmrp_adjustment/tests/test_adu_dlt_adjustment.py
odoo/addons/ddmrp_adjustment/tests/test_common.py
odoo/addons/ddmrp_adjustment/views/ddmrp_adjustment_demand_view.xml
odoo/addons/ddmrp_adjustment/views/ddmrp_adjustment_view.xml
odoo/addons/ddmrp_adjustment/views/stock_warehouse_orderpoint.xml
odoo/addons/ddmrp_adjustment/wizards/__init__.py
odoo/addons/ddmrp_adjustment/wizards/ddmrp_adjustment_sheet.py
odoo/addons/ddmrp_adjustment/wizards/ddmrp_adjustment_wizard_view.xml
odoo11_addon_ddmrp_adjustment-11.0.1.1.0.99.dev5.dist-info/METADATA
odoo11_addon_ddmrp_adjustment-11.0.1.1.0.99.dev5.dist-info/WHEEL
odoo11_addon_ddmrp_adjustment-11.0.1.1.0.99.dev5.dist-info/top_level.txt
odoo11_addon_ddmrp_adjustment-11.0.1.1.0.99.dev5.dist-info/RECORD
